gempaterkini/__init__.py
latestearthquake_indonesia_khoolid-0.0.1.dist-info/LICENSE
latestearthquake_indonesia_khoolid-0.0.1.dist-info/METADATA
latestearthquake_indonesia_khoolid-0.0.1.dist-info/WHEEL
latestearthquake_indonesia_khoolid-0.0.1.dist-info/top_level.txt
latestearthquake_indonesia_khoolid-0.0.1.dist-info/RECORD
