Metadata-Version: 2.1
Name: latestearthquake-indonesia-khoolid
Version: 0.0.1
Summary: A small example package
Author-email: Saif Kholid <kholidsaif312@gmail.com>
License: GNU GENERAL PUBLIC LICENSE
Project-URL: Bug Tracker, https://github.com/pypa/sampleproject/issues
Project-URL: Homepage, https://github.com/Kholid0803/indonesia-latest-earthquake
Classifier: Programming Language :: Python :: 3
Classifier: License :: OSI Approved :: GNU General Public License v3 (GPLv3)
Classifier: Operating System :: OS Independent
Classifier: Development Status :: 4 - Beta
Requires-Python: >=3.7
License-File: LICENSE
